vsdrba_distilled/__init__.py
vsdrba_distilled/__main__.py
vsdrba_distilled/distilDRBA.py
vsdrba_distilled/distilDRBA_v2_lite.py
vsdrba_distilled/warplayer.py
vsdrba_distilled/.ipynb_checkpoints/__init__-checkpoint.py
vsdrba_distilled/.ipynb_checkpoints/__main__-checkpoint.py
vsdrba_distilled-1.0.0.dist-info/METADATA
vsdrba_distilled-1.0.0.dist-info/WHEEL
vsdrba_distilled-1.0.0.dist-info/licenses/LICENSE
vsdrba_distilled-1.0.0.dist-info/RECORD
